[{"name":"Mohamed Salah","chunk":0},{"name":"Heung-Min Son","chunk":0},{"name":"Harry Kane","chunk":0},{"name":"Kevin De Bruyne","chunk":0},{"name":"Trent Alexander-Arnold","chunk":0},{"name":"Jamie Vardy","chunk":0},{"name":"Andrew Robertson","chunk":0},{"name":"Jordan Pickford","chunk":0},{"name":"Raheem Sterling (Man City)","chunk":0},{"name":"Marcus Rashford (Man Utd)","chunk":0},{"name":"Virgil van Dijk","chunk":0},{"name":"Ederson Santana de Moraes","chunk":0},{"name":"Sadio Mané","chunk":0},{"name":"Riyad Mahrez","chunk":0},{"name":"Alisson Ramses Becker","chunk":0},{"name":"Roberto Firmino","chunk":0},{"name":"James Maddison","chunk":0},{"name":"Wilfried Zaha","chunk":0},{"name":"Hugo Lloris","chunk":0},{"name":"Kyle Walker","chunk":0},{"name":"Bukayo Saka","chunk":0},{"name":"Lukasz Fabianski","chunk":0},{"name":"Jarrod Bowen","chunk":0},{"name":"Nick Pope","chunk":0},{"name":"Gabriel Fernando de Jesus","chunk":0},{"name":"Callum Wilson","chunk":0},{"name":"Richarlison de Andrade","chunk":0},{"name":"Ollie Watkins","chunk":0},{"name":"Michail Antonio","chunk":0},{"name":"James Tarkowski","chunk":0},{"name":"César Azpilicueta","chunk":0},{"name":"Abdoulaye Doucouré","chunk":0},{"name":"Christian Eriksen","chunk":0},{"name":"Phil Foden","chunk":0},{"name":"James Ward-Prowse (Southampton)","chunk":0},{"name":"Pascal Groß","chunk":0},{"name":"Declan Rice","chunk":0},{"name":"Ilkay Gündogan","chunk":0},{"name":"Marcos Alonso","chunk":0},{"name":"Lewis Dunk","chunk":0},{"name":"Harvey Barnes","chunk":0},{"name":"Kasper Schmeichel","chunk":0},{"name":"Raúl Jiménez","chunk":0},{"name":"Harry Maguire","chunk":0},{"name":"Dominic Calvert-Lewin","chunk":0},{"name":"Bernd Leno","chunk":0},{"name":"Michael Keane","chunk":0},{"name":"Ben Mee","chunk":0},{"name":"Dwight McNeil","chunk":0},{"name":"Anthony Martial","chunk":0},{"name":"Youri Tielemans","chunk":1},{"name":"Sergio Agüero","chunk":1},{"name":"Pierre-Emerick Aubameyang","chunk":1},{"name":"Kieran Trippier","chunk":1},{"name":"Martin Ødegaard","chunk":1},{"name":"Aaron Cresswell","chunk":1},{"name":"Aaron Wan-Bissaka","chunk":1},{"name":"Bamidele Alli (Spurs)","chunk":1},{"name":"Gylfi Sigurdsson","chunk":1},{"name":"David de Gea","chunk":1},{"name":"Erling Haaland","chunk":1},{"name":"Nathan Aké","chunk":1},{"name":"Fabian Schär","chunk":1},{"name":"Andros Townsend","chunk":1},{"name":"Alexandre Lacazette","chunk":1},{"name":"Granit Xhaka","chunk":1},{"name":"Paul Pogba","chunk":1},{"name":"Danny Welbeck","chunk":1},{"name":"Eden Hazard","chunk":1},{"name":"Bryan Mbeumo","chunk":1},{"name":"Bernardo Mota Veiga de Carvalho e Silva","chunk":1},{"name":"Joshua King","chunk":1},{"name":"John Stones","chunk":1},{"name":"Pierre-Emile Højbjerg","chunk":1},{"name":"Seamus Coleman","chunk":1},{"name":"Nathan Redmond","chunk":1},{"name":"Eberechi Eze","chunk":1},{"name":"Willian Borges Da Silva","chunk":1},{"name":"John McGinn","chunk":1},{"name":"Jonny Evans","chunk":1},{"name":"Romelu Lukaku","chunk":1},{"name":"Jack Harrison","chunk":1},{"name":"Ben Foster","chunk":1},{"name":"Mason Mount","chunk":1},{"name":"Kai Havertz","chunk":1},{"name":"David Silva","chunk":1},{"name":"Luke Shaw","chunk":1},{"name":"Jack Grealish","chunk":1},{"name":"Eric Dier","chunk":1},{"name":"Rodrigo Hernandez","chunk":1},{"name":"Matt Doherty","chunk":1},{"name":"Jordan Henderson","chunk":1},{"name":"Joel Matip","chunk":1},{"name":"Ezri Konsa Ngoyo","chunk":1},{"name":"Victor Lindelöf","chunk":1},{"name":"Vicente Guaita","chunk":1},{"name":"Jeffrey Schlupp","chunk":1},{"name":"Martin Dubravka (Newcastle)","chunk":1},{"name":"Georginio Wijnaldum","chunk":1},{"name":"Douglas Luiz Soares de Paulo","chunk":1},{"name":"Luka Milivojevic","chunk":2},{"name":"Jordan Ayew (Crystal Palace)","chunk":2},{"name":"Antonio Rüdiger","chunk":2},{"name":"Wilfred Ndidi","chunk":2},{"name":"Aymeric Laporte","chunk":2},{"name":"Ashley Young","chunk":2},{"name":"Tyrone Mings","chunk":2},{"name":"James Milner","chunk":2},{"name":"Alexis Mac Allister","chunk":2},{"name":"Cheikhou Kouyaté","chunk":2},{"name":"Yoane Wissa","chunk":2},{"name":"Jacob Murphy","chunk":2},{"name":"N'Golo Kanté","chunk":2},{"name":"Bruno Borges Fernandes","chunk":2},{"name":"Bruno Miguel Borges Fernandes","chunk":2},{"name":"James McArthur","chunk":2},{"name":"Benjamin Chilwell","chunk":2},{"name":"Chris Wood (Burnley)","chunk":2},{"name":"Ayoze Pérez","chunk":2},{"name":"Tyrick Mitchell","chunk":2},{"name":"Kelechi Iheanacho","chunk":2},{"name":"Patrick van Aanholt","chunk":2},{"name":"Adama Traoré","chunk":2},{"name":"Joelinton Cássio Apolinário de Lira","chunk":2},{"name":"Robert Sánchez","chunk":2},{"name":"José Malheiro de Sá","chunk":2},{"name":"Adam Smith","chunk":2},{"name":"Joel Ward","chunk":2},{"name":"Jorge Luiz Frello Filho (Chelsea)","chunk":2},{"name":"Alexander Isak","chunk":2},{"name":"Oleksandr Zinchenko","chunk":2},{"name":"Idrissa Gueye","chunk":2},{"name":"Demarai Gray","chunk":2},{"name":"Alexis Sánchez","chunk":2},{"name":"David Luiz Moreira Marinho","chunk":2},{"name":"Bruno Guimarães Rodriguez Moura","chunk":2},{"name":"Christian Benteke","chunk":2},{"name":"Cole Palmer (Chelsea)","chunk":2},{"name":"Manuel Lanzini","chunk":2},{"name":"João Filipe Iria Santos Moutinho","chunk":2},{"name":"Conor Coady (Wolves)","chunk":2},{"name":"Toby Alderweireld","chunk":2},{"name":"Angelo Ogbonna","chunk":2},{"name":"Ben Davies (Spurs)","chunk":2},{"name":"Ashley Westwood","chunk":2},{"name":"Ryan Fraser (Bournemouth)","chunk":2},{"name":"Luis Díaz","chunk":2},{"name":"Héctor Bellerín","chunk":2},{"name":"Leandro Trossard (Arsenal)","chunk":2},{"name":"Max Kilman","chunk":2},{"name":"Fernando Luiz Rosa","chunk":3},{"name":"Dejan Kulusevski","chunk":3},{"name":"Leroy Sané","chunk":3},{"name":"Morgan Gibbs-White (Nott'm Forest)","chunk":3},{"name":"Gabriel Martinelli Silva","chunk":3},{"name":"Ashley Barnes","chunk":3},{"name":"Ryan Bertrand","chunk":3},{"name":"Jay Rodriguez","chunk":3},{"name":"Jan Bednarek (Southampton)","chunk":3},{"name":"Marc Albrighton","chunk":3},{"name":"Timothy Castagne","chunk":3},{"name":"Jesse Lingard (Man Utd)","chunk":3},{"name":"Jean-Philippe Mateta","chunk":3},{"name":"Scott McTominay","chunk":3},{"name":"Troy Deeney","chunk":3},{"name":"Pedro Lomba Neto","chunk":3},{"name":"Matthew Lowton","chunk":3},{"name":"Dominic Solanke","chunk":3},{"name":"Jamaal Lascelles","chunk":3},{"name":"Lucas Rodrigues Moura da Silva","chunk":3},{"name":"Nélson Cabral Semedo","chunk":3},{"name":"Reece James","chunk":3},{"name":"Mathew Ryan (Brighton)","chunk":3},{"name":"Mesut Özil","chunk":3},{"name":"Danny Ings (Southampton)","chunk":3},{"name":"Davinson Sánchez","chunk":3},{"name":"Che Adams","chunk":3},{"name":"Gabriel dos Santos Magalhães","chunk":3},{"name":"William Saliba","chunk":3},{"name":"Nicolás Otamendi","chunk":3},{"name":"Salomón Rondón","chunk":3},{"name":"Conor Gallagher","chunk":3},{"name":"Mark Noble","chunk":3},{"name":"Charlie Taylor","chunk":3},{"name":"Rui Pedro dos Santos Patrício","chunk":3},{"name":"Serge Aurier","chunk":3},{"name":"Stuart Armstrong","chunk":3},{"name":"Tomas Soucek","chunk":3},{"name":"Rúben Diogo da Silva Neves","chunk":3},{"name":"Marc Guéhi","chunk":3},{"name":"Adam Lallana","chunk":3},{"name":"Nemanja Matic","chunk":3},{"name":"Alex McCarthy","chunk":3},{"name":"Lucas Digne (Everton)","chunk":3},{"name":"Oriol Romeu Vidal","chunk":3},{"name":"Matt Ritchie","chunk":3},{"name":"Sean Longstaff","chunk":3},{"name":"Kepa Arrizabalaga (Chelsea)","chunk":3},{"name":"Joël Veltman","chunk":3},{"name":"Jan Vertonghen","chunk":3},{"name":"Jack Cork","chunk":4},{"name":"Benjamin White","chunk":4},{"name":"Pedro Rodríguez Ledesma","chunk":4},{"name":"João Pedro Cavaco Cancelo","chunk":4},{"name":"Fabio Henrique Tavares","chunk":4},{"name":"Marko Arnautovic","chunk":4},{"name":"Ivan Toney","chunk":4},{"name":"Gary Cahill","chunk":4},{"name":"Leandro Trossard (Brighton)","chunk":4},{"name":"Cédric Soares","chunk":4},{"name":"Adam Webster","chunk":4},{"name":"Nathaniel Clyne","chunk":4},{"name":"Jonjo Shelvey (Newcastle)","chunk":4},{"name":"Johann Berg Gudmundsson","chunk":4},{"name":"Jacob Ramsey","chunk":4},{"name":"Anthony Elanga","chunk":4},{"name":"Xherdan Shaqiri","chunk":4},{"name":"Olivier Giroud","chunk":4},{"name":"Federico Fernández","chunk":4},{"name":"Jeff Hendrick","chunk":4},{"name":"Emiliano Martínez Romero","chunk":4},{"name":"Emile Smith Rowe","chunk":4},{"name":"Antonee Robinson","chunk":4},{"name":"Allan Saint-Maximin","chunk":4},{"name":"Kyle Walker-Peters","chunk":4},{"name":"Romain Saïss","chunk":4},{"name":"Bernardo Veiga de Carvalho e Silva","chunk":4},{"name":"Fraser Forster","chunk":4},{"name":"James Tomkins","chunk":4},{"name":"Christian Nørgaard","chunk":4},{"name":"Juan Mata","chunk":4},{"name":"Steve Cook","chunk":4},{"name":"Matheus Santos Carneiro Da Cunha","chunk":4},{"name":"Illan Meslier","chunk":4},{"name":"Philip Billing","chunk":4},{"name":"Lewis Cook","chunk":4},{"name":"Yves Bissouma","chunk":4},{"name":"Vitaly Janelt","chunk":4},{"name":"Dan Burn (Newcastle)","chunk":4},{"name":"Mario Lemina","chunk":4},{"name":"Vitalii Mykolenko","chunk":4},{"name":"Alex Oxlade-Chamberlain","chunk":4},{"name":"Erik Pieters","chunk":4},{"name":"Saïd Benrahma","chunk":4},{"name":"Etienne Capoue","chunk":4},{"name":"Solomon March","chunk":4},{"name":"Thomas Partey","chunk":4},{"name":"Pablo Fornals","chunk":4},{"name":"Jack Stephens (Southampton)","chunk":4},{"name":"Joseph Gomez","chunk":4},{"name":"Neal Maupay (Brighton)","chunk":5},{"name":"Nacho Monreal","chunk":5},{"name":"Leon Bailey","chunk":5},{"name":"Ricardo Domingos Barbosa Pereira","chunk":5},{"name":"Harry Wilson","chunk":5},{"name":"Andreas Hoelgebaum Pereira","chunk":5},{"name":"Chris Wood (Nott'm Forest)","chunk":5},{"name":"Michael Olise","chunk":5},{"name":"Mason Holgate (Everton)","chunk":5},{"name":"Jonathan Castro Otto","chunk":5},{"name":"Ethan Pinnock","chunk":5},{"name":"Shkodran Mustafi","chunk":5},{"name":"Christian Pulisic","chunk":5},{"name":"Joachim Andersen (Crystal Palace)","chunk":5},{"name":"Cody Gakpo","chunk":5},{"name":"Mathias Jensen","chunk":5},{"name":"Alex Iwobi (Everton)","chunk":5},{"name":"Matt Targett (Aston Villa)","chunk":5},{"name":"Alphonse Areola","chunk":5},{"name":"Mateo Kovacic","chunk":5},{"name":"Emiliano Martínez (Aston Villa)","chunk":5},{"name":"Nathan Collins","chunk":5},{"name":"Frederico Rodrigues de Paula Santos","chunk":5},{"name":"Patrick Bamford","chunk":5},{"name":"Shane Duffy","chunk":5},{"name":"Andre Gray","chunk":5},{"name":"Tammy Abraham","chunk":5},{"name":"Kieran Tierney","chunk":5},{"name":"Thiago Emiliano da Silva","chunk":5},{"name":"Diogo Dalot Teixeira","chunk":5},{"name":"Lucas Digne (Aston Villa)","chunk":5},{"name":"Anthony Gordon (Newcastle)","chunk":5},{"name":"Roberto Pereyra","chunk":5},{"name":"Robert Snodgrass (West Ham)","chunk":5},{"name":"Willy Boly (Wolves)","chunk":5},{"name":"Leander Dendoncker (Wolves)","chunk":5},{"name":"Rodrigo Moreno","chunk":5},{"name":"Tom Davies","chunk":5},{"name":"Aaron Ramsdale (Arsenal)","chunk":5},{"name":"Darwin Núñez Ribeiro","chunk":5},{"name":"Dejan Lovren","chunk":5},{"name":"Aaron Ramsey","chunk":5},{"name":"Edouard Mendy","chunk":5},{"name":"Miguel Almirón","chunk":5},{"name":"João Pedro Junqueira de Jesus","chunk":5},{"name":"Pedro Porro","chunk":5},{"name":"Moussa Sissoko (Spurs)","chunk":5},{"name":"Antoine Semenyo","chunk":5},{"name":"Tosin Adarabioyo","chunk":5},{"name":"Cristian Romero","chunk":5}]